{"name":"Bagas's Mod","tagline":"little knowledge about mods can lead you to an big success :)..","body":"\r\n\r\n![](http://www.droid-life.com/wp-content/uploads/2012/04/Minecraft-Logo.png)\r\n\r\n### Welcome to my page.\r\n\r\nHello guys, this is my official page for my mods. almost all of my mods is herobrine mod, im herobrine's fan, lol.\r\n\r\n`function visitorHook() {\r\n  clientMessage(\"Hello!\")\r\n    I.give(thanks)`\r\n\r\n\r\n\r\n### About me\r\nI am a modder, i like herobrine, he is cool, but dangerous sometimes, and herobrine does not exist in MCPE, so i created some mods to add him in game, im working on Extreme Herobrine 3, version Alpha 4.0, its going to be a huge mod.\r\n\r\nP.S I'am an animator too lol :P\r\n\r\n### Mods\r\nMy mods:\r\n* Extreme Herobrine\r\n* Extreme Herobrine 2\r\n* Extreme Herobrine 3\r\n* Herobrine Kit 1.3\r\n* Entity 303 Boss Battle\r\n* AltBrine\r\n* SuperBrine\r\n* Enderman voices(WARNING DO NOT USE THIS)\r\n\r\n### Copyright for my mods\r\n© 2014 Bagas\r\n\r\nCopyright: YOU ARE NOT ALLOWED TO COPY, EDIT, AND CLAIM AS IF ITS YOUR MOD, DOING SO WILL BE BANNED FROM THE SITE.\r\n\r\n","google":"","note":"Don't delete this file! It's used internally to help with page regeneration."}